punchline/__init__.py
punchline/__main__.py
punchline/_cli.py
punchline/_melody.py
punchline/_music_box.py
punchline/_staves.py
punchline-1.4.0.dist-info/LICENSE
punchline-1.4.0.dist-info/WHEEL
punchline-1.4.0.dist-info/METADATA
punchline-1.4.0.dist-info/RECORD
