Metadata-Version: 2.1
Name: punchline
Version: 1.4.0
Summary: CLI tool to generate SVG punch cards for a DIY music box from MIDI melodies.
Keywords: music box,music,midi,svg,punchcards,diy
Author-email: Gram <gram@orsinium.dev>
Requires-Python: >=3.9
Classifier: Development Status :: 5 - Production/Stable
Classifier: Intended Audience :: Developers
Classifier: License :: OSI Approved :: MIT License
Classifier: Programming Language :: Python
Classifier: Topic :: Multimedia :: Sound/Audio
Classifier: Topic :: Multimedia :: Sound/Audio :: MIDI
Classifier: Typing :: Typed
Requires-Dist: svg.py>=1.1.0
Requires-Dist: mido
Requires-Dist: pytest ; extra == "test"
Project-URL: Source, https://github.com/orsinium-labs/punchline
Provides-Extra: test
